license
lospec2aseprite/__init__.py
lospec2aseprite/importer.py
lospec2aseprite/template.json
lospec2aseprite-0.1.1.dist-info/entry_points.txt
lospec2aseprite-0.1.1.dist-info/license
lospec2aseprite-0.1.1.dist-info/WHEEL
lospec2aseprite-0.1.1.dist-info/METADATA
lospec2aseprite-0.1.1.dist-info/RECORD
