Metadata-Version: 2.1
Name: lospec2aseprite
Version: 0.1.1
Summary: Import palettes from Lospec to Aseprite
Home-page: https://github.com/Konosprod/lospec2aseprite
License: MIT
Author: Konosprod
Author-email: konosprod@free.fr
Requires-Python: >=3.7,<4.0
Classifier: Environment :: Console
Classifier: Intended Audience :: End Users/Desktop
Classifier: License :: OSI Approved :: MIT License
Classifier: Programming Language :: Python :: 3
Classifier: Programming Language :: Python :: 3.7
Classifier: Programming Language :: Python :: 3.8
Classifier: Topic :: Utilities
Requires-Dist: beautifulsoup4 (>=4.9.1,<5.0.0)
Requires-Dist: progressbar2 (>=3.51.4,<4.0.0)
Requires-Dist: requests_download (>=0.1.2,<0.2.0)
